PyDistLinalg/__init__.py.py
PyDistLinalg/config.py
PyDistLinalg/core.py
PyDistLinalg/decompositions.py
PyDistLinalg/interface.py
PyDistLinalg/solvers.py
PyDistLinalg/utils.py
pydistlinalg-0.0.1.dist-info/licenses/LICENSE
pydistlinalg-0.0.1.dist-info/METADATA
pydistlinalg-0.0.1.dist-info/WHEEL
pydistlinalg-0.0.1.dist-info/top_level.txt
pydistlinalg-0.0.1.dist-info/RECORD
